blacksheep_jwt/__init__.py
blacksheep_jwt/authentication.py
blacksheep_jwt/backends.py
blacksheep_jwt/errors.py
blacksheep_jwt/settings.py
blacksheep_jwt/tokens.py
blacksheep_jwt/utils.py
blacksheep_jwt-0.1.0.dist-info/WHEEL
blacksheep_jwt-0.1.0.dist-info/METADATA
blacksheep_jwt-0.1.0.dist-info/LICENSE
blacksheep_jwt-0.1.0.dist-info/RECORD
